netbox_license/__init__.py
netbox_license/choices.py
netbox_license/events.py
netbox_license/graphql.py
netbox_license/jobs.py
netbox_license/navigation.py
netbox_license/search.py
netbox_license/signals.py
netbox_license/tables.py
netbox_license/template_content.py
netbox_license/urls.py
netbox_license/version.py
netbox_license/api/__init__.py
netbox_license/api/serializers.py
netbox_license/api/urls.py
netbox_license/api/views.py
netbox_license/api/serializers/__init__.py
netbox_license/api/serializers/licenses.py
netbox_license/filtersets/__init__.py
netbox_license/filtersets/licenseassignments.py
netbox_license/filtersets/licenses.py
netbox_license/filtersets/licensetypes.py
netbox_license/forms/__init__.py
netbox_license/forms/bulk_edit.py
netbox_license/forms/bulk_import.py
netbox_license/forms/filtersets.py
netbox_license/forms/models.py
netbox_license/management/commands/check_expiring_licenses.py
netbox_license/migrations/0001_initial.py
netbox_license/migrations/0002_remove_license_manufacturer_and_more.py
netbox_license/migrations/0003_license_status.py
netbox_license/migrations/0004_rename_assigned_to_licenseassignment_assigned_on.py
netbox_license/migrations/__init__.py
netbox_license/models/__init__.py
netbox_license/models/license.py
netbox_license/models/licenseassignment.py
netbox_license/models/licensetype.py
netbox_license/templates/netbox_license/license.html
netbox_license/templates/netbox_license/licenseassignment.html
netbox_license/templates/netbox_license/licensetype.html
netbox_license/templates/netbox_license/inc/clusters_info.html
netbox_license/templates/netbox_license/inc/device_info.html
netbox_license/templates/netbox_license/inc/license_progressbar.html
netbox_license/templates/netbox_license/inc/licensetype_related.html
netbox_license/templates/netbox_license/inc/virtual_machines_info.html
netbox_license/utils/__init__.py
netbox_license/views/__init__.py
netbox_license/views/license.py
netbox_license/views/licenseassignment.py
netbox_license-2.3.0.dist-info/METADATA
netbox_license-2.3.0.dist-info/WHEEL
netbox_license-2.3.0.dist-info/top_level.txt
netbox_license-2.3.0.dist-info/RECORD
