Metadata-Version: 2.4
Name: netbox_license
Version: 2.3.0
Summary: Inventory License management in NetBox
Author-email: Kobe Naessens <kobenaessens04@gmail.com>
Keywords: netbox,netbox-plugin,License
Classifier: Programming Language :: Python :: 3
Classifier: License :: OSI Approved :: MIT License
Classifier: Operating System :: OS Independent
Requires-Python: >=3.10
